docnext/__init__.py
docnext/blocks/__init__.py
docnext/blocks/block.py
docnext/blocks/code_block.py
docnext/blocks/eval_block.py
docnext/blocks/exec_block.py
docnext/blocks/markdown_block.py
docnext/cli.py
docnext/constants.py
docnext/docnext.py
docnext/document.py
docnext/errors.py
docnext/templates/__init__.py
docnext/templates/base_template.py
docnext/types.py
docnext/utils.py
docnext-0.1.1a0.dist-info/METADATA
docnext-0.1.1a0.dist-info/WHEEL
docnext-0.1.1a0.dist-info/entry_points.txt
docnext-0.1.1a0.dist-info/RECORD
