Metadata-Version: 2.1
Name: docnext
Version: 0.1.1a0
Summary: Convert Markdown Documentation to beautiful sites. Built on top of flexdown
Author: Team dotagent
Author-email: anurag@dotagent.ai
Requires-Python: >=3.9,<4.0
Classifier: Programming Language :: Python :: 3
Classifier: Programming Language :: Python :: 3.9
Classifier: Programming Language :: Python :: 3.10
Classifier: Programming Language :: Python :: 3.11
Requires-Dist: mistletoe (>=1.2.1,<2.0.0)
Requires-Dist: nextpy (>=0.1.4,<0.2.0)
Requires-Dist: pyyaml (>=6.0.1,<7.0.0)
